pyhidra/__init__.py
pyhidra/__main__.py
pyhidra/converters.py
pyhidra/core.py
pyhidra/gui.py
pyhidra/install_desktop.py
pyhidra/install_plugins.py
pyhidra/javac.py
pyhidra/launcher.py
pyhidra/linux_shortcut.py
pyhidra/mac_shortcut.py
pyhidra/properties.py
pyhidra/script.py
pyhidra/uninstall_desktop.py
pyhidra/uninstall_plugin.py
pyhidra/version.py
pyhidra/win_shortcut.py
pyhidra/java/__init__.py
pyhidra/java/plugin/PyScriptProviderNew.java
pyhidra/java/plugin/PyScriptProviderOld.java
pyhidra/java/plugin/PyhidraPlugin.java
pyhidra/java/plugin/PythonFieldExposer.java
pyhidra/java/plugin/__init__.py
pyhidra/java/plugin/completions.py
pyhidra/java/plugin/plugin.py
pyhidra/java/plugin/ghidra_scripts/PyhidraBasics.py
pyhidra/java/plugin/interpreter/CancelAction.java
pyhidra/java/plugin/interpreter/InterpreterGhidraScript.java
pyhidra/java/plugin/interpreter/InterpreterTaskMonitor.java
pyhidra/java/plugin/interpreter/PyhidraInterpreterConnection.java
pyhidra/java/plugin/interpreter/RestartAction.java
pyhidra/java/property/AbstractJavaProperty.java
pyhidra/java/property/BooleanJavaProperty.java
pyhidra/java/property/ByteJavaProperty.java
pyhidra/java/property/CharacterJavaProperty.java
pyhidra/java/property/DoubleJavaProperty.java
pyhidra/java/property/FloatJavaProperty.java
pyhidra/java/property/IntegerJavaProperty.java
pyhidra/java/property/JavaProperty.java
pyhidra/java/property/JavaPropertyFactory.java
pyhidra/java/property/LongJavaProperty.java
pyhidra/java/property/ObjectJavaProperty.java
pyhidra/java/property/PropertyUtils.java
pyhidra/java/property/ShortJavaProperty.java
pyhidra-1.3.0.dist-info/LICENSE
pyhidra-1.3.0.dist-info/METADATA
pyhidra-1.3.0.dist-info/WHEEL
pyhidra-1.3.0.dist-info/entry_points.txt
pyhidra-1.3.0.dist-info/top_level.txt
pyhidra-1.3.0.dist-info/RECORD
