Metadata-Version: 2.1
Name: pyhidra
Version: 1.3.0
Summary: Native CPython for Ghidra
Home-page: https://github.com/Defense-Cyber-Crime-Center/pyhidra
Author: DC3
Author-email: dcci@dc3.mil
License: MIT
Keywords: ghidra
Platform: any
Classifier: Development Status :: 5 - Production/Stable
Classifier: Intended Audience :: Developers
Classifier: License :: OSI Approved :: MIT License
Classifier: Programming Language :: Python :: 3
Classifier: Programming Language :: Python :: 3.9
Classifier: Programming Language :: Python :: 3.10
Classifier: Programming Language :: Python :: 3.11
Classifier: Programming Language :: Python :: 3.12
Requires-Python: >=3.9
License-File: LICENSE
Requires-Dist: Jpype1>=1.3.0; python_version < "3.12"
Requires-Dist: Jpype1>=1.5.0; python_version >= "3.12"
Requires-Dist: packaging
Provides-Extra: testing
Requires-Dist: pytest; extra == "testing"
Requires-Dist: pytest-datadir; extra == "testing"
